setup.py
dsn_wechat/__init__.py
dsn_wechat/crypto.py
dsn_wechat/menu.py
dsn_wechat/messages.py
dsn_wechat/oauth2.py
dsn_wechat_client.egg-info/PKG-INFO
dsn_wechat_client.egg-info/SOURCES.txt
dsn_wechat_client.egg-info/dependency_links.txt
dsn_wechat_client.egg-info/not-zip-safe
dsn_wechat_client.egg-info/requires.txt
dsn_wechat_client.egg-info/top_level.txt
test/test_wechat_messages.py